{
  "rowId": 95,
  "Tijdschrift_ID_Nieuw": "T00347",
  "Uitgever-z": true,
  "Plaats1_opmerking": "",
  "Plaats-z": true,
  "Uitgever_vanaf": "",
  "Uitgever2-z": false,
  "Drukker-z": false,
  "Politiek?": true,
  "Niet_bewaard": false,
  "VGB": false,
  "Lidwoord Titel": "",
  "Titel1": "Sincerus aan het Bataafsche volk",
  "Titel2": "",
  "Titel2_vanaf": "",
  "Titel3": "",
  "Titel3_vanaf": "",
  "Titel4": "",
  "Titel4_vanaf": "",
  "Titel5": "",
  "Titel5_vanaf": "",
  "Titel6": "",
  "Titel6_vaf": "",
  "Titel7": "",
  "Titel7_vanaf": "",
  "Ondertitel": "",
  "Motto": "",
  "Frequentie": "Wekelijks",
  "Frequentie-z": true,
  "Eerste_nr_MAAND": "7",
  "Eerste_nr_MAAND_z": true,
  "Eerste_nr_JAAR": "1798",
  "Eerste_nr_JAAR-z": true,
  "Eerste_nr_EDTF": "1798-07",
  "Laatste_nr_maand": "10",
  "Laatste_nr_maand-z": true,
  "Laatste_nr_JAAR": "1798",
  "Laatste_nr_JAAR-z": true,
  "Laatste_nr_EDTF": "1798-10",
  "Prijs_duiten": "12",
  "Afleveringen": "10",
  "Afleveringen-z": false,
  "Dagen/Info": "",
  "Formaat": "Groot Octavo",
  "Datering": "In het eerste nummer wordt vooruit gewezen naar '10 juli aanstaande'. Het tweede nummer verscheen na die datum.",
  "Zie_ID_Vervolgtitel_van": "",
  "Zie_ook_1_ID": "",
  "Zie_ook_2_ID": "",
  "Vorm_Tijdschrift": "Overige",
  "Type_Tijdschrift": "Politiek",
  "Overige overheidsstukken": false,
  "Dialogen": false,
  "Satire": false,
  "Notulen en handelingen": false,
  "Nieuwsberichten": false,
  "vorm_Mengelwerk": false,
  "Advertenties": false,
  "Decreten en proclamaties": false,
  "Ingezonden brieven": false,
  "Redactionele betogen": true,
  "Toelichting_redacteur-auteur": "",
  "Duiding_van_de_titel": "",
  "Verantwoording_selectie": "",
  "Korte_omschrijving_inhoud": "Het blad verzette zich in het eerste nummer op inhoudelijke wijze tegen de staatsgreep van 12 juni en het stelde zich vervolgens kritisch op. In redactionele betogen werd met name gewaakt voor vermeende federalistische tendensen in het nieuwe Uitvoerend Bewind. Het analyseerde de consequenties van de bestuurlijke herindeling in 1798 en besteedde aandacht aan de oplossingen die door het nieuwe bewind werden aangevoerd om de 'partijzucht' te verminderen. Het blad verklaarde het gebrek aan eenheid onder de Bataven vanuit de sociale structuur van de maatschappij.",
  "Politieke-Positie": "Radicaal",
  "Politieke_positie_toelichting": "",
  "Doel van het tijdschrift": "",
  "Oplage en bereik": "",
  "Reactie_en_of_justitie": "",
  "Advertenties_en_andere_verwijsplaatsen": "",
  "Opmerkingen": "In nummer 2 sprak de auteur van een herdruk van het eerste nummer, wat hem ertoe bewoog het tijdschrift voort te zetten.\n \nIn nummer 3 stelde de auteur dat zijn naam bekend is bij de uitgever en daar door justitie kan worden opgevraagd, maar dat hij hem niet openbaar maakt, uit vrees dat lezers zijn stukken op voorhand zouden goedkeuren of afwijzen 'alleen op het zien van de ondertekening'.",
  "Opmaak_en_spelling": "Wisselend klassiek en modern d/t-gebruik, (niet consequent) IJ i.p.v. Y",
  "Bewaarplaats": "Utrecht, UB Bijzondere Collecties: Convoluut Br 175 14 (nummers 1-10)",
  "Apparaat_Hanou": "",
  "Apparaat_Kluit": "Weekbladen 1798 S Staatkundige",
  "Digitaal_exemplaar": "Nee",
  "Links_naar_Saakes_1": "https://books.google.ch/books?id=V8teAAAAcAAJ&pg=PA473&lpg=PA473",
  "Link_naar_Saakes_2": "https://books.google.ch/books?id=V8teAAAAcAAJ&pg=PA506",
  "Link_naar_Saakes_3": "",
  "STCN": "http://picarta.pica.nl/DB=3.11/XMLPRS=Y/PPN?PPN=244840113",
  "ENT": "",
  "Seclit1_titel": "",
  "Seclit2_titel": "",
  "Sectlit3_titel": "",
  "Seclit4_titel": "",
  "Uitgever": {
    "id": "U00008",
    "rowId": 205,
    "Uitgeverij": "Andries Balster",
    "Bestaan": "1796-1798",
    "Plaats1": {
      "id": "PL00003",
      "rowId": 3,
      "name": "Amsterdam",
      "country": "Netherlands",
      "country_GeoNames": "NL",
      "Latitude": 52.37302,
      "Longitude": 4.89856,
      "GeoNames_uri": "http://sws.geonames.org/2759793/"
    },
    "Plaats2": null,
    "Plaats3": null
  },
  "Uitgever2": null,
  "Drukker": null,
  "Plaats1": {
    "id": "PL00003",
    "rowId": 3,
    "name": "Amsterdam",
    "country": "Netherlands",
    "country_GeoNames": "NL",
    "Latitude": 52.37302,
    "Longitude": 4.89856,
    "GeoNames_uri": "http://sws.geonames.org/2759793/"
  },
  "Plaats2": null,
  "Plaats3": null,
  "Auteur_Redacteur1": null,
  "Auteur_Redacteur2": null,
  "Auteur_Redacteur3": null,
  "Auteur_Redacteur4": null,
  "Auteur_Redacteur5": null
}